CHANGES.txt
LICENSE
MANIFEST.in
README.rst
requirements.txt
setup.py
retrosynthesis/__init__.py
retrosynthesis/bibtex.py
retrosynthesis/constants.py
retrosynthesis/objects.py
retrosynthesis/wizard_retrosynthesis.py
retrosynthesis/protocols/__init__.py
retrosynthesis/protocols/protocol_retrosynthesis.py
retrosynthesis/tests/__init__.py
retrosynthesis/tests/tests_retrosynthesis.py
retrosynthesis/viewers/__init__.py
retrosynthesis/viewers/viewers_retrosynthesis.py
retrosynthesis/wizards/__init__.py
retrosynthesis/wizards/wizard_retrosynthesis.py
scipion_chem_retrosynthesis.egg-info/PKG-INFO
scipion_chem_retrosynthesis.egg-info/SOURCES.txt
scipion_chem_retrosynthesis.egg-info/dependency_links.txt
scipion_chem_retrosynthesis.egg-info/entry_points.txt
scipion_chem_retrosynthesis.egg-info/requires.txt
scipion_chem_retrosynthesis.egg-info/top_level.txt