Metadata-Version: 2.1
Name: scipion-chem-retrosynthesis
Version: 0.2
Summary: Scipion framework plugin for the use of retrosynthesis software tools
Home-page: https://github.com/scipion-chem/scipion-chem-retrosynthesis
Author: Martín Salinas
Author-email: martin.salinas@cnb.csic.es
Keywords: scipion retrosynthesis scipion-3.0 cheminformatics
License-File: LICENSE
Requires-Dist: scipion-pyworkflow
Requires-Dist: scipion-em
Requires-Dist: scipion-chem
